moloni/__init__.py
moloni/__version__.py
moloni/api/__init__.py
moloni/api/bankaccounts_client.py
moloni/api/billsoflading_client.py
moloni/api/companies_client.py
moloni/api/countries_client.py
moloni/api/creditnotes_client.py
moloni/api/currencies_client.py
moloni/api/customeralternateaddresses_client.py
moloni/api/customerreturnnotes_client.py
moloni/api/customers_client.py
moloni/api/debitnotes_client.py
moloni/api/deductions_client.py
moloni/api/deliverymethods_client.py
moloni/api/deliverynotes_client.py
moloni/api/documentmodels_client.py
moloni/api/documents_client.py
moloni/api/documentsets_client.py
moloni/api/estimates_client.py
moloni/api/fiscalzones_client.py
moloni/api/identificationtemplates_client.py
moloni/api/invoicereceipts_client.py
moloni/api/invoices_client.py
moloni/api/languages_client.py
moloni/api/maturitydates_client.py
moloni/api/measurementunits_client.py
moloni/api/ownassetsmovementguides_client.py
moloni/api/paymentmethods_client.py
moloni/api/productcategories_client.py
moloni/api/products_client.py
moloni/api/receipts_client.py
moloni/api/salesmen_client.py
moloni/api/simplifiedinvoices_client.py
moloni/api/subscription_client.py
moloni/api/suppliers_client.py
moloni/api/taxes_client.py
moloni/api/taxexemptions_client.py
moloni/api/users_client.py
moloni/api/vehicles_client.py
moloni/api/warehouses_client.py
moloni/api/waybills_client.py
moloni/base/__init__.py
moloni/base/client.py
moloni/base/config.py
moloni/base/helpers.py
moloni/base/logger_config.py
python_moloni-0.3.15.dist-info/LICENSE
python_moloni-0.3.15.dist-info/METADATA
python_moloni-0.3.15.dist-info/WHEEL
python_moloni-0.3.15.dist-info/top_level.txt
python_moloni-0.3.15.dist-info/RECORD
