Metadata-Version: 2.1
Name: python-moloni
Version: 0.3.15
Summary: Python wrapper for the Moloni API
Home-page: https://github.com/saleweaver/python-moloni
Author: Michael
Author-email: michael@datastic.co
License: MIT
Platform: UNKNOWN
License-File: LICENSE
Requires-Dist: requests
Requires-Dist: cachetools>=4.2
Requires-Dist: pydantic
Provides-Extra: aws
Requires-Dist: boto3; extra == "aws"
Provides-Extra: aws-caching
Requires-Dist: aws-secretsmanager-caching; extra == "aws-caching"
Requires-Dist: boto3; extra == "aws-caching"
